Workbook

Sheet Instrucciones
A1: Metodología y matriz de evaluación de riesgos de IA
A2: Plantilla de apoyo de la guía Descifrando ISO 42001. Interpretación del autor; no sustituye a la norma ISO/IEC 42001 ni es asesoría legal. Los nombres de los controles son traducciones libres.
A4: 1. Revisa y ajusta la hoja Criterios: escalas de consecuencia (para la organización, para individuos y para la sociedad), escala de probabilidad, matriz de clasificación y tabla de aceptación. Apruébalas como criterios de riesgo de IA (cláusula 6.1.1).
A5: 2. En Registro de riesgos, identifica cada riesgo por sistema de IA (o grupo de sistemas), con su fuente de riesgo (inspirada en el Anexo C) y su descripción en formato causa → evento → consecuencia.
A6: 3. Califica la consecuencia en las tres dimensiones. La consecuencia que cuenta es la PEOR de las tres (no el promedio): un riesgo puede ser leve para la organización y grave para las personas.
A7: 4. Califica la probabilidad (cuando aplique). La clasificación se obtiene de la matriz asimétrica de la hoja Criterios, que pesa más la consecuencia que la probabilidad.
A8: 5. Define el tratamiento, los controles del Anexo A y los controles propios, y vuelve a calificar el riesgo residual. Registra quién aprueba la aceptación del riesgo residual según la tabla de aceptación (6.1.3).
A9: 6. Usa los resultados de las evaluaciones de impacto (6.1.4) para calificar la consecuencia para individuos y sociedad.
A10: 7. Las hojas Mapa inherente y Mapa residual cuentan los riesgos en cada celda de la matriz 5 × 5.
A11: 8. Las filas de ejemplo corresponden a la empresa ficticia Monarca Crédito (caso práctico 2) y coinciden con el ejemplo resuelto de la cláusula 6 en la guía.
A13: Autor: Carlos Adrián Guzmán · Descifrando ISO 42001 · Licencia CC BY-SA 4.0 · https://adriangzmncrz-arch.github.io/descifrando-iso42001/

Sheet Criterios
A1: Criterios de riesgo de IA
A2: Ajusta descriptores, matriz y tabla de aceptación a tu contexto y apruébalos (6.1.1).
A4: Nivel | B4: Consecuencia | C4: Para la organización | D4: Para individuos o grupos | E4: Para la sociedad
A5: 1 | B5: Insignificante | C5: Sin pérdida relevante ni atención externa | D5: Molestia que se corrige en el momento | E5: Sin efecto perceptible
A6: 2 | B6: Menor | C6: Pérdida que el área absorbe; queja aislada | D6: Error que la persona corrige sola en días, sin costo | E6: Efecto local y aislado
A7: 3 | B7: Moderada | C7: Reasignar presupuesto; requerimiento de una autoridad; quejas repetidas | D7: Afectación reversible con esfuerzo a derechos u oportunidades | E7: Afecta de forma reversible a un segmento identificable
A8: 4 | B8: Mayor | C8: Sanción; pérdida de un cliente clave o de una alianza; prensa negativa | D8: Daño significativo y difícil de revertir: discriminación sistemática, exposición de datos sensibles | E8: Refuerza desigualdades o daña la confianza en un sector
A9: 5 | B9: Severa | C9: Amenaza la continuidad del negocio o la licencia para operar | D9: Daño grave o irreversible a la vida, la salud, la libertad o el patrimonio | E9: Efecto sistémico o duradero en servicios esenciales o procesos democráticos
A12: Nivel | B12: Probabilidad | C12: Descripción | D12: Guía de frecuencia (ejemplo)
A13: 1 | B13: Rara | C13: No se espera en la vida del sistema | D13: Menos de una vez en cinco años o de 1 en 1 000 000 de decisiones
A14: 2 | B14: Improbable | C14: Ha ocurrido en otras organizaciones, no en la nuestra | D14: Una vez cada dos a cinco años
A15: 3 | B15: Posible | C15: Antecedentes internos aislados | D15: Una vez al año
A16: 4 | B16: Probable | C16: Se observa varias veces al año o en las pruebas | D16: Trimestral o más de 1 en 10 000 decisiones
A17: 5 | B17: Casi segura | C17: Ya está ocurriendo de forma recurrente | D17: Mensual o más de 1 en 1 000 decisiones
A19: Matriz de clasificación (filas: consecuencia · columnas: probabilidad). Edita los textos si cambias tu apetito de riesgo.
A21: C \ P | B21: 1 | C21: 2 | D21: 3 | E21: 4 | F21: 5
A22: 5 | B22: Alto | C22: Alto | D22: Crítico | E22: Crítico | F22: Crítico
A23: 4 | B23: Medio | C23: Alto | D23: Alto | E23: Crítico | F23: Crítico
A24: 3 | B24: Bajo | C24: Medio | D24: Alto | E24: Alto | F24: Crítico
A25: 2 | B25: Bajo | C25: Bajo | D25: Medio | E25: Medio | F25: Alto
A26: 1 | B26: Bajo | C26: Bajo | D26: Bajo | E26: Medio | F26: Medio
A29: Nivel | B29: Decisión | C29: Plazo | D29: Quién acepta el residual | E29: Revisión
A30: Bajo | B30: Aceptable con los controles existentes | C30: Sin plan | D30: Dueño del sistema de IA | E30: Anual
A31: Medio | B31: Aceptable con monitoreo; tratar si el costo es razonable | C31: 6 meses, si se trata | D31: Responsable del SGIA | E31: Semestral
A32: Alto | B32: No aceptable sin tratamiento | C32: Plan en 30 días; ejecución en 90 | D32: Comité de IA o dirección designada, informando a la alta dirección | E32: Trimestral
A33: Crítico | B33: Inaceptable: no se lanza o se suspende la función | C33: Inmediato | D33: Sin aceptación permanente; excepción temporal solo con firma de la dirección general | E33: Mensual
A35: Líneas rojas (no pasan por la matriz): incumplir deliberadamente una ley aplicable, desplegar un uso de IA prohibido en alguna jurisdicción donde operas o usar datos personales para una finalidad no informada.

Sheet Registro de riesgos
A1: Registro de riesgos de IA
A2: Cláusulas 6.1.2, 6.1.3, 8.2 y 8.3
A4: ID | B4: Sistema de IA | C4: Fuente de riesgo | D4: Descripción (causa → evento → consecuencia) | E4: Dueño del riesgo | F4: Consecuencia organización | G4: Consecuencia individuos | H4: Consecuencia sociedad | I4: Consecuencia (peor) | J4: Probabilidad | K4: Clasificación inherente | L4: Tratamiento | M4: Controles del Anexo A | N4: Controles propios o adicionales | O4: Consecuencia residual | P4: Probabilidad residual | Q4: Clasificación residual | R4: ¿Residual aceptado? | S4: Aprobado por | T4: Estado | U4: Fecha de evaluación
A5: R-01 | B5: Score Monarca v3 | C5: Aprendizaje automático (datos y entrenamiento) | D5: Variables sustitutas: el código postal se correlaciona con región e ingreso → el modelo podría rechazar de forma desproporcionada a solicitantes de ciertas entidades → negación de crédito a grupos enteros | E5: Director de Riesgos | F5: 4 | G5: 4 | H5: 3 | I5: =IF(COUNT(F5:H5)=0,"",MAX(F5:H5)) | J5: 3 | K5: =IF(OR(I5="",J5=""),"",INDEX(Criterios!$B$22:$F$26,6-I5,J5)) | L5: Mitigar | M5: A.7.4, A.7.6, A.6.2.4, A.5.4 | N5: C-MOD-01 prueba de variables sustitutas en cada reentrenamiento | O5: 4 | P5: 1 | Q5: =IF(OR(O5="",P5=""),"",INDEX(Criterios!$B$22:$F$26,6-O5,P5)) | R5: Sí | S5: Comité de Modelos | T5: En tratamiento | U5: 46338
A6: R-02 | B6: Score Monarca v3 | C6: Ciclo de vida del sistema | D6: Deriva económica: cambios en inflación y empleo → los solicitantes dejan de parecerse a los de entrenamiento → morosidad y rechazos injustos | E6: Líder de Ciencia de Datos | F6: 4 | G6: 3 | H6: 2 | I6: =IF(COUNT(F6:H6)=0,"",MAX(F6:H6)) | J6: 4 | K6: =IF(OR(I6="",J6=""),"",INDEX(Criterios!$B$22:$F$26,6-I6,J6)) | L6: Mitigar | M6: A.6.2.6, A.6.2.8, A.6.2.5 | N6: C-MON-02 interruptor: si el índice de estabilidad poblacional supera el umbral interno, todo pasa a la banda gris | O6: 3 | P6: 2 | Q6: =IF(OR(O6="",P6=""),"",INDEX(Criterios!$B$22:$F$26,6-O6,P6)) | R6: Sí | S6: Comité de Modelos | T6: En tratamiento | U6: 46338
A7: R-03 | B7: Score Monarca v3 | C7: Falta de transparencia o explicabilidad | D7: Rechazos sin explicación: el rechazo automático muestra un mensaje genérico → los solicitantes no pueden entender ni impugnar la decisión → quejas ante la autoridad de protección al usuario financiero | E7: Oficial de Cumplimiento | F7: 3 | G7: 4 | H7: 2 | I7: =IF(COUNT(F7:H7)=0,"",MAX(F7:H7)) | J7: 4 | K7: =IF(OR(I7="",J7=""),"",INDEX(Criterios!$B$22:$F$26,6-I7,J7)) | L7: Mitigar | M7: A.8.2, A.8.3, A.6.2.7 | N7: C-EXP-01 motivos en lenguaje claro probados con usuarios | O7: 2 | P7: 3 | Q7: =IF(OR(O7="",P7=""),"",INDEX(Criterios!$B$22:$F$26,6-O7,P7)) | R7: Sí | S7: Comité de Modelos | T7: En tratamiento | U7: 46338
A8: R-04 | B8: Score Monarca v3 | C8: Privacidad y datos personales | D8: Datos fuera de finalidad: variables de uso de la app recolectadas para otra finalidad del aviso de privacidad → se usan en el modelo sin base adecuada → posible incumplimiento de la ley de datos personales | E8: Oficial de Privacidad | F8: 4 | G8: 3 | H8: 1 | I8: =IF(COUNT(F8:H8)=0,"",MAX(F8:H8)) | J8: 2 | K8: =IF(OR(I8="",J8=""),"",INDEX(Criterios!$B$22:$F$26,6-I8,J8)) | L8: Evitar | M8: A.7.3, A.7.5, A.4.3, A.2.3 | N8: Retiro de las dos variables | O8: 4 | P8: 1 | Q8: =IF(OR(O8="",P8=""),"",INDEX(Criterios!$B$22:$F$26,6-O8,P8)) | R8: Sí | S8: Comité de Modelos | T8: Tratado | U8: 46338
A9: R-05 | B9: Score Monarca v3 | C9: Nivel de automatización | D9: Sesgo de automatización: por carga de trabajo, los analistas confirman casi siempre la sugerencia del modelo → la supervisión humana de la banda gris se vuelve ineficaz | E9: Director de Riesgos | F9: 3 | G9: 4 | H9: 2 | I9: =IF(COUNT(F9:H9)=0,"",MAX(F9:H9)) | J9: 3 | K9: =IF(OR(I9="",J9=""),"",INDEX(Criterios!$B$22:$F$26,6-I9,J9)) | L9: Mitigar | M9: A.9.3, A.4.6, A.6.2.6 | N9: C-HUM-01: 5 % de la banda gris se presenta sin el score | O9: 4 | P9: 2 | Q9: =IF(OR(O9="",P9=""),"",INDEX(Criterios!$B$22:$F$26,6-O9,P9)) | R9: Temporal | S9: Comité de Modelos | T9: En tratamiento | U9: 46338
I10: =IF(COUNT(F10:H10)=0,"",MAX(F10:H10)) | K10: =IF(OR(I10="",J10=""),"",INDEX(Criterios!$B$22:$F$26,6-I10,J10)) | Q10: =IF(OR(O10="",P10=""),"",INDEX(Criterios!$B$22:$F$26,6-O10,P10))
I11: =IF(COUNT(F11:H11)=0,"",MAX(F11:H11)) | K11: =IF(OR(I11="",J11=""),"",INDEX(Criterios!$B$22:$F$26,6-I11,J11)) | Q11: =IF(OR(O11="",P11=""),"",INDEX(Criterios!$B$22:$F$26,6-O11,P11))
I12: =IF(COUNT(F12:H12)=0,"",MAX(F12:H12)) | K12: =IF(OR(I12="",J12=""),"",INDEX(Criterios!$B$22:$F$26,6-I12,J12)) | Q12: =IF(OR(O12="",P12=""),"",INDEX(Criterios!$B$22:$F$26,6-O12,P12))
I13: =IF(COUNT(F13:H13)=0,"",MAX(F13:H13)) | K13: =IF(OR(I13="",J13=""),"",INDEX(Criterios!$B$22:$F$26,6-I13,J13)) | Q13: =IF(OR(O13="",P13=""),"",INDEX(Criterios!$B$22:$F$26,6-O13,P13))
I14: =IF(COUNT(F14:H14)=0,"",MAX(F14:H14)) | K14: =IF(OR(I14="",J14=""),"",INDEX(Criterios!$B$22:$F$26,6-I14,J14)) | Q14: =IF(OR(O14="",P14=""),"",INDEX(Criterios!$B$22:$F$26,6-O14,P14))
I15: =IF(COUNT(F15:H15)=0,"",MAX(F15:H15)) | K15: =IF(OR(I15="",J15=""),"",INDEX(Criterios!$B$22:$F$26,6-I15,J15)) | Q15: =IF(OR(O15="",P15=""),"",INDEX(Criterios!$B$22:$F$26,6-O15,P15))
I16: =IF(COUNT(F16:H16)=0,"",MAX(F16:H16)) | K16: =IF(OR(I16="",J16=""),"",INDEX(Criterios!$B$22:$F$26,6-I16,J16)) | Q16: =IF(OR(O16="",P16=""),"",INDEX(Criterios!$B$22:$F$26,6-O16,P16))
I17: =IF(COUNT(F17:H17)=0,"",MAX(F17:H17)) | K17: =IF(OR(I17="",J17=""),"",INDEX(Criterios!$B$22:$F$26,6-I17,J17)) | Q17: =IF(OR(O17="",P17=""),"",INDEX(Criterios!$B$22:$F$26,6-O17,P17))
I18: =IF(COUNT(F18:H18)=0,"",MAX(F18:H18)) | K18: =IF(OR(I18="",J18=""),"",INDEX(Criterios!$B$22:$F$26,6-I18,J18)) | Q18: =IF(OR(O18="",P18=""),"",INDEX(Criterios!$B$22:$F$26,6-O18,P18))
I19: =IF(COUNT(F19:H19)=0,"",MAX(F19:H19)) | K19: =IF(OR(I19="",J19=""),"",INDEX(Criterios!$B$22:$F$26,6-I19,J19)) | Q19: =IF(OR(O19="",P19=""),"",INDEX(Criterios!$B$22:$F$26,6-O19,P19))
I20: =IF(COUNT(F20:H20)=0,"",MAX(F20:H20)) | K20: =IF(OR(I20="",J20=""),"",INDEX(Criterios!$B$22:$F$26,6-I20,J20)) | Q20: =IF(OR(O20="",P20=""),"",INDEX(Criterios!$B$22:$F$26,6-O20,P20))
I21: =IF(COUNT(F21:H21)=0,"",MAX(F21:H21)) | K21: =IF(OR(I21="",J21=""),"",INDEX(Criterios!$B$22:$F$26,6-I21,J21)) | Q21: =IF(OR(O21="",P21=""),"",INDEX(Criterios!$B$22:$F$26,6-O21,P21))
... I154: =IF(COUNT(F154:H154)=0,"",MAX(F154:H154)) | K154: =IF(OR(I154="",J154=""),"",INDEX(Criterios!$B$22:$F$26,6-I154,J154)) | Q154: =IF(OR(O154="",P154=""),"",INDEX(Criterios!$B$22:$F$26,6-O154,P154))

Sheet Listas
A1: Fuente | B1: Tratamiento | C1: Estado | D1: SiNo
A2: Complejidad del entorno | B2: Mitigar | C2: Identificado | D2: Sí
A3: Falta de transparencia o explicabilidad | B3: Evitar | C3: En tratamiento | D3: No
A4: Nivel de automatización | B4: Transferir o compartir | C4: Tratado | D4: Temporal
A5: Aprendizaje automático (datos y entrenamiento) | B5: Aceptar | C5: Aceptado
A6: Hardware e infraestructura | B6: Aprovechar (oportunidad) | C6: Cerrado
A7: Ciclo de vida del sistema
A8: Madurez tecnológica
A9: Proveedor o tercero
A10: Uso indebido previsible
A11: Seguridad propia de la IA
A12: Privacidad y datos personales
A13: Otra

Sheet Mapa inherente
A1: Mapa inherente de riesgos de IA
A2: Cada celda cuenta los riesgos del registro con esa consecuencia y probabilidad.
B4: Consecuencia ↓ / Probabilidad →
C5: 1 · Rara | D5: 2 · Improbable | E5: 3 · Posible | F5: 4 · Probable | G5: 5 · Casi segura
B6: 5 · Severa | C6: =COUNTIFS('Registro de riesgos'!$I$5:$I$154,5,'Registro de riesgos'!$J$5:$J$154,1) | D6: =COUNTIFS('Registro de riesgos'!$I$5:$I$154,5,'Registro de riesgos'!$J$5:$J$154,2) | E6: =COUNTIFS('Registro de riesgos'!$I$5:$I$154,5,'Registro de riesgos'!$J$5:$J$154,3) | F6: =COUNTIFS('Registro de riesgos'!$I$5:$I$154,5,'Registro de riesgos'!$J$5:$J$154,4) | G6: =COUNTIFS('Registro de riesgos'!$I$5:$I$154,5,'Registro de riesgos'!$J$5:$J$154,5)
B7: 4 · Mayor | C7: =COUNTIFS('Registro de riesgos'!$I$5:$I$154,4,'Registro de riesgos'!$J$5:$J$154,1) | D7: =COUNTIFS('Registro de riesgos'!$I$5:$I$154,4,'Registro de riesgos'!$J$5:$J$154,2) | E7: =COUNTIFS('Registro de riesgos'!$I$5:$I$154,4,'Registro de riesgos'!$J$5:$J$154,3) | F7: =COUNTIFS('Registro de riesgos'!$I$5:$I$154,4,'Registro de riesgos'!$J$5:$J$154,4) | G7: =COUNTIFS('Registro de riesgos'!$I$5:$I$154,4,'Registro de riesgos'!$J$5:$J$154,5)
B8: 3 · Moderada | C8: =COUNTIFS('Registro de riesgos'!$I$5:$I$154,3,'Registro de riesgos'!$J$5:$J$154,1) | D8: =COUNTIFS('Registro de riesgos'!$I$5:$I$154,3,'Registro de riesgos'!$J$5:$J$154,2) | E8: =COUNTIFS('Registro de riesgos'!$I$5:$I$154,3,'Registro de riesgos'!$J$5:$J$154,3) | F8: =COUNTIFS('Registro de riesgos'!$I$5:$I$154,3,'Registro de riesgos'!$J$5:$J$154,4) | G8: =COUNTIFS('Registro de riesgos'!$I$5:$I$154,3,'Registro de riesgos'!$J$5:$J$154,5)
B9: 2 · Menor | C9: =COUNTIFS('Registro de riesgos'!$I$5:$I$154,2,'Registro de riesgos'!$J$5:$J$154,1) | D9: =COUNTIFS('Registro de riesgos'!$I$5:$I$154,2,'Registro de riesgos'!$J$5:$J$154,2) | E9: =COUNTIFS('Registro de riesgos'!$I$5:$I$154,2,'Registro de riesgos'!$J$5:$J$154,3) | F9: =COUNTIFS('Registro de riesgos'!$I$5:$I$154,2,'Registro de riesgos'!$J$5:$J$154,4) | G9: =COUNTIFS('Registro de riesgos'!$I$5:$I$154,2,'Registro de riesgos'!$J$5:$J$154,5)
B10: 1 · Insignificante | C10: =COUNTIFS('Registro de riesgos'!$I$5:$I$154,1,'Registro de riesgos'!$J$5:$J$154,1) | D10: =COUNTIFS('Registro de riesgos'!$I$5:$I$154,1,'Registro de riesgos'!$J$5:$J$154,2) | E10: =COUNTIFS('Registro de riesgos'!$I$5:$I$154,1,'Registro de riesgos'!$J$5:$J$154,3) | F10: =COUNTIFS('Registro de riesgos'!$I$5:$I$154,1,'Registro de riesgos'!$J$5:$J$154,4) | G10: =COUNTIFS('Registro de riesgos'!$I$5:$I$154,1,'Registro de riesgos'!$J$5:$J$154,5)
B12: Los colores siguen la matriz por defecto. Si cambias la matriz en Criterios, ajusta también estos colores.

Sheet Mapa residual
A1: Mapa residual de riesgos de IA
A2: Cada celda cuenta los riesgos del registro con esa consecuencia y probabilidad.
B4: Consecuencia ↓ / Probabilidad →
C5: 1 · Rara | D5: 2 · Improbable | E5: 3 · Posible | F5: 4 · Probable | G5: 5 · Casi segura
B6: 5 · Severa | C6: =COUNTIFS('Registro de riesgos'!$O$5:$O$154,5,'Registro de riesgos'!$P$5:$P$154,1) | D6: =COUNTIFS('Registro de riesgos'!$O$5:$O$154,5,'Registro de riesgos'!$P$5:$P$154,2) | E6: =COUNTIFS('Registro de riesgos'!$O$5:$O$154,5,'Registro de riesgos'!$P$5:$P$154,3) | F6: =COUNTIFS('Registro de riesgos'!$O$5:$O$154,5,'Registro de riesgos'!$P$5:$P$154,4) | G6: =COUNTIFS('Registro de riesgos'!$O$5:$O$154,5,'Registro de riesgos'!$P$5:$P$154,5)
B7: 4 · Mayor | C7: =COUNTIFS('Registro de riesgos'!$O$5:$O$154,4,'Registro de riesgos'!$P$5:$P$154,1) | D7: =COUNTIFS('Registro de riesgos'!$O$5:$O$154,4,'Registro de riesgos'!$P$5:$P$154,2) | E7: =COUNTIFS('Registro de riesgos'!$O$5:$O$154,4,'Registro de riesgos'!$P$5:$P$154,3) | F7: =COUNTIFS('Registro de riesgos'!$O$5:$O$154,4,'Registro de riesgos'!$P$5:$P$154,4) | G7: =COUNTIFS('Registro de riesgos'!$O$5:$O$154,4,'Registro de riesgos'!$P$5:$P$154,5)
B8: 3 · Moderada | C8: =COUNTIFS('Registro de riesgos'!$O$5:$O$154,3,'Registro de riesgos'!$P$5:$P$154,1) | D8: =COUNTIFS('Registro de riesgos'!$O$5:$O$154,3,'Registro de riesgos'!$P$5:$P$154,2) | E8: =COUNTIFS('Registro de riesgos'!$O$5:$O$154,3,'Registro de riesgos'!$P$5:$P$154,3) | F8: =COUNTIFS('Registro de riesgos'!$O$5:$O$154,3,'Registro de riesgos'!$P$5:$P$154,4) | G8: =COUNTIFS('Registro de riesgos'!$O$5:$O$154,3,'Registro de riesgos'!$P$5:$P$154,5)
B9: 2 · Menor | C9: =COUNTIFS('Registro de riesgos'!$O$5:$O$154,2,'Registro de riesgos'!$P$5:$P$154,1) | D9: =COUNTIFS('Registro de riesgos'!$O$5:$O$154,2,'Registro de riesgos'!$P$5:$P$154,2) | E9: =COUNTIFS('Registro de riesgos'!$O$5:$O$154,2,'Registro de riesgos'!$P$5:$P$154,3) | F9: =COUNTIFS('Registro de riesgos'!$O$5:$O$154,2,'Registro de riesgos'!$P$5:$P$154,4) | G9: =COUNTIFS('Registro de riesgos'!$O$5:$O$154,2,'Registro de riesgos'!$P$5:$P$154,5)
B10: 1 · Insignificante | C10: =COUNTIFS('Registro de riesgos'!$O$5:$O$154,1,'Registro de riesgos'!$P$5:$P$154,1) | D10: =COUNTIFS('Registro de riesgos'!$O$5:$O$154,1,'Registro de riesgos'!$P$5:$P$154,2) | E10: =COUNTIFS('Registro de riesgos'!$O$5:$O$154,1,'Registro de riesgos'!$P$5:$P$154,3) | F10: =COUNTIFS('Registro de riesgos'!$O$5:$O$154,1,'Registro de riesgos'!$P$5:$P$154,4) | G10: =COUNTIFS('Registro de riesgos'!$O$5:$O$154,1,'Registro de riesgos'!$P$5:$P$154,5)
B12: Los colores siguen la matriz por defecto. Si cambias la matriz en Criterios, ajusta también estos colores.
